cmsplugin_yandex_maps/__init__.py
cmsplugin_yandex_maps/addon_urls.py
cmsplugin_yandex_maps/admin.py
cmsplugin_yandex_maps/apps.py
cmsplugin_yandex_maps/cms_apps.py
cmsplugin_yandex_maps/cms_plugins.py
cmsplugin_yandex_maps/forms.py
cmsplugin_yandex_maps/models.py
cmsplugin_yandex_maps/urls.py
cmsplugin_yandex_maps/views.py
cmsplugin_yandex_maps/fixtures/cmsplugin_yandex_maps.xml
cmsplugin_yandex_maps/locale/ru_RU/LC_MESSAGES/django.mo
cmsplugin_yandex_maps/locale/ru_RU/LC_MESSAGES/django.po
cmsplugin_yandex_maps/migrations/0001_initial.py
cmsplugin_yandex_maps/migrations/0002_load_init_data.py
cmsplugin_yandex_maps/migrations/0003_auto_20170207_0923.py
cmsplugin_yandex_maps/migrations/0004_from_fk_to_m2m.py
cmsplugin_yandex_maps/migrations/0005_collections_claster_routes.py
cmsplugin_yandex_maps/migrations/__init__.py
cmsplugin_yandex_maps/static/cmsplugin_yandex_maps/css/ColorInput.css
cmsplugin_yandex_maps/static/cmsplugin_yandex_maps/img/save.png
cmsplugin_yandex_maps/static/cmsplugin_yandex_maps/js/ClasterAdmin.js
cmsplugin_yandex_maps/static/cmsplugin_yandex_maps/js/CollectionAdmin.js
cmsplugin_yandex_maps/static/cmsplugin_yandex_maps/js/IconStyleAdmin.js
cmsplugin_yandex_maps/static/cmsplugin_yandex_maps/js/PlacemarkAdmin.js
cmsplugin_yandex_maps/static/cmsplugin_yandex_maps/js/RouteAdmin.js
cmsplugin_yandex_maps/static/cmsplugin_yandex_maps/js/YandexMapsAdmin.js
cmsplugin_yandex_maps/static/cmsplugin_yandex_maps/js/utils.js
cmsplugin_yandex_maps/templates/cmsplugin_yandex_maps/yandex_maps.djhtml
cmsplugin_yandex_maps/templates/cmsplugin_yandex_maps/includes/placemark_properties.djhtml
cmsplugin_yandex_maps/tests/__init__.py
cmsplugin_yandex_maps/tests/runtests.py
cmsplugin_yandex_maps/tests/settings.py
cmsplugin_yandex_maps/tests/test_forms.py
cmsplugin_yandex_maps/tests/test_models.py
cmsplugin_yandex_maps/tests/test_plugins.py
cmsplugin_yandex_maps/tests/test_views.py
cmsplugin_yandex_maps/tests/urls.py
cmsplugin_yandex_maps-0.4.4.dist-info/DESCRIPTION.rst
cmsplugin_yandex_maps-0.4.4.dist-info/METADATA
cmsplugin_yandex_maps-0.4.4.dist-info/RECORD
cmsplugin_yandex_maps-0.4.4.dist-info/WHEEL
cmsplugin_yandex_maps-0.4.4.dist-info/metadata.json
cmsplugin_yandex_maps-0.4.4.dist-info/top_level.txt
