Metadata-Version: 2.0
Name: cmsplugin-yandex-maps
Version: 0.4.4
Summary: Rich functionality Yandex Maps plugin for Django-CMS
Home-page: https://github.com/Atterratio/cmsplugin-yandex-maps
Author: Aeternus Atterratio
Author-email: atterratio@gmail.com
License: MIT
Keywords: Django Django-CMS Yandex Map
Platform: UNKNOWN
Classifier: Development Status :: 4 - Beta
Classifier: Environment :: Web Environment
Classifier: Framework :: Django
Classifier: License :: OSI Approved :: MIT License
Classifier: Operating System :: OS Independent
Classifier: Programming Language :: Python :: 3
Classifier: Programming Language :: Python :: 3.3
Classifier: Programming Language :: Python :: 3.4
Classifier: Programming Language :: Python :: 3.5
Classifier: Programming Language :: Python :: 3.6
Classifier: Topic :: Internet :: WWW/HTTP
Classifier: Topic :: Internet :: WWW/HTTP :: Dynamic Content
Classifier: Topic :: Software Development :: Libraries :: Application Frameworks
Classifier: Topic :: Software Development :: Libraries :: Python Modules
Requires-Dist: django (>=1.8.0)
Requires-Dist: django-cms (>=3.3.0)
Requires-Dist: unidecode
